fluttrfly/__init__.py
fluttrfly/assets/config.json
fluttrfly/bin/__init__.py
fluttrfly/bin/commands/__init__.py
fluttrfly/bin/commands/build_command.py
fluttrfly/bin/commands/env_command.py
fluttrfly/bin/commands/global_variables.py
fluttrfly/bin/commands/setup_command.py
fluttrfly/bin/entry.py
fluttrfly/bin/functions/__init__.py
fluttrfly/bin/functions/build_functions.py
fluttrfly/bin/functions/common_functions.py
fluttrfly/bin/functions/env_functions.py
fluttrfly/bin/functions/json_functions.py
fluttrfly/bin/functions/setup_functions.py
fluttrfly/bin/manager/__init__.py
fluttrfly/bin/manager/command_lines.py
fluttrfly/bin/manager/commands_manager.py
fluttrfly-2.0.4.dist-info/LICENSE
fluttrfly-2.0.4.dist-info/METADATA
fluttrfly-2.0.4.dist-info/WHEEL
fluttrfly-2.0.4.dist-info/entry_points.txt
fluttrfly-2.0.4.dist-info/RECORD
