Metadata-Version: 2.1
Name: fluttrfly
Version: 2.0.4
Summary: a versatile CLI tool that automates the creation of essential project structures.
License: MIT
Author: Bharath ram
Author-email: bharathram123@gmail.com
Requires-Python: >=3.9,<4.0
Classifier: License :: OSI Approved :: MIT License
Classifier: Programming Language :: Python :: 3
Classifier: Programming Language :: Python :: 3.9
Classifier: Programming Language :: Python :: 3.10
Classifier: Programming Language :: Python :: 3.11
Requires-Dist: click (>=8.1.7,<9.0.0)
Requires-Dist: pyyaml (>=6.0.2,<7.0.0)
Requires-Dist: rich (>=13.7.0,<14.0.0)
